{"num_shadows": 1000, "gs_nrg_tap": "-54.629778458820105", "gs_nrg_tap_cst": "(-36.91053028221503+2.557907421889684e-16j)", "gs_nrg_tap_cst_up": "(-36.47022416269292-5.635119093166973e-16j)", "shadow": {"0": [["z", "z", "y", "x", "z", "y", "x", "z", "z", "z"], "0100011001"], "1": [["y", "z", "x", "y", "x", "z", "y", "z", "z", "z"], "0101111101"], "2": [["x", "z", "x", "y", "z", "x", "y", "y", "x", "z"], "0010111001"], "3": [["z", "x", "y", "y", "y", "y", "z", "z", "x", "x"], "0101100000"], "4": [["z", "x", "x", "y", "y", "y", "x", "y", "z", "y"], "1101001010"], "5": [["x", "x", "y", "z", "y", "z", "z", "x", "x", "z"], "0001110111"], "6": [["x", "y", "z", "x", "y", "y", "z", "y", "x", "x"], "1001101000"], "7": [["x", "y", "y", "y", "x", "x", "x", "x", "x", "z"], "0100001001"], "8": [["y", "y", "x", "y", "z", "z", "x", "y", "z", "x"], "0101111001"], "9": [["y", "y", "x", "z", "x", "x", "x", "y", "z", "z"], "0111010000"], "10": [["y", "x", "z", "z", "x", "z", "z", "x", "z", "x"], "0100100010"], "11": [["x", "y", "x", "y", "x", "z", "x", "x", "z", "z"], "0101111100"], "12": [["x", "z", "y", "y", "y", "z", "x", "z", "y", "y"], "0000101001"], "13": [["x", "x", "x", "z", "z", "z", "x", "z", "y", "z"], "0100110101"], "14": [["y", "y", "z", "z", "z", "y", "x", "z", "x", "z"], "0100110011"], "15": [["x", "x", "y", "x", "z", "z", "y", "z", "y", "x"], "1000111111"], "16": [["z", "x", "x", "z", "y", "z", "y", "y", "x", "z"], "0100100010"], "17": [["y", "y", "y", "z", "x", "x", "x", "y", "x", "x"], "0010000011"], "18": [["y", "y", "x", "x", "y", "z", "x", "x", "y", "y"], "1001100101"], "19": [["x", "x", "x", "y", "z", "z", "y", "x", "x", "z"], "0010111000"], "20": [["y", "y", "y", "y", "x", "y", "z", "z", "z", "y"], "0101011101"], "21": [["y", "z", "z", "z", "z", "y", "x", "x", "x", "x"], "0101110000"], "22": [["z", "y", "z", "x", "y", "y", "x", "y", "x", "z"], "0100110000"], "23": [["z", "y", "z", "x", "z", "z", "x", "x", "y", "z"], "0101110000"], "24": [["z", "z", "x", "y", "x", "x", "x", "y", "x", "z"], "0100101000"], "25": [["z", "x", "x", "y", "z", "y", "z", "z", "y", "x"], "1001110000"], "26": [["z", "z", "z", "y", "z", "y", "y", "x", "z", "z"], "0101110000"], "27": [["x", "y", "x", "x", "y", "y", "x", "x", "y", "z"], "0000100011"], "28": [["z", "x", "z", "y", "x", "x", "y", "x", "z", "x"], "1110001000"], "29": [["x", "x", "z", "x", "z", "y", "y", "z", "y", "x"], "0001110011"], "30": [["z", "z", "z", "z", "x", "x", "x", "y", "z", "y"], "0101110000"], "31": [["z", "x", "y", "z", "x", "z", "y", "y", "y", "z"], "0100110100"], "32": [["z", "y", "z", "z", "x", "z", "z", "z", "x", "y"], "1101100000"], "33": [["x", "x", "y", "x", "y", "y", "x", "z", "x", "y"], "0001010110"], "34": [["y", "z", "y", "z", "y", "y", "x", "y", "y", "z"], "0110010101"], "35": [["y", "y", "x", "x", "y", "x", "z", "y", "x", "y"], "1001101101"], "36": [["x", "z", "z", "y", "z", "x", "x", "z", "x", "x"], "0100110001"], "37": [["y", "x", "x", "x", "z", "x", "y", "y", "z", "z"], "0110011010"], "38": [["x", "z", "y", "z", "z", "y", "z", "y", "y", "z"], "0101110000"], "39": [["z", "x", "z", "x", "y", "y", "z", "x", "z", "x"], "1101001010"], "40": [["y", "y", "x", "x", "x", "z", "y", "y", "y", "x"], "0010110000"], "41": [["x", "y", "z", "y", "z", "z", "x", "z", "y", "z"], "0001111010"], "42": [["z", "y", "z", "y", "y", "y", "z", "z", "x", "y"], "0101101010"], "43": [["x", "x", "y", "x", "y", "x", "z", "z", "z", "x"], "0101000011"], "44": [["z", "y", "x", "z", "z", "z", "y", "z", "x", "x"], "0001110100"], "45": [["y", "x", "y", "x", "x", "x", "x", "y", "x", "y"], "1010101110"], "46": [["x", "y", "x", "z", "z", "x", "x", "y", "x", "z"], "0001110000"], "47": [["y", "x", "x", "x", "z", "x", "y", "x", "x", "x"], "1111110000"], "48": [["y", "x", "y", "y", "z", "y", "z", "z", "y", "y"], "0101110101"], "49": [["z", "z", "z", "x", "x", "x", "z", "y", "z", "z"], "0111001000"], "50": [["x", "x", "x", "y", "x", "y", "x", "z", "x", "x"], "1000100110"], "51": [["y", "x", "y", "x", "y", "y", "y", "y", "x", "z"], "0110010000"], "52": [["y", "y", "y", "x", "y", "x", "y", "x", "y", "x"], "0000110111"], "53": [["y", "y", "x", "z", "z", "x", "x", "x", "z", "x"], "1111010000"], "54": [["z", "x", "y", "z", "z", "z", "x", "x", "x", "x"], "0010110000"], "55": [["x", "z", "x", "y", "y", "z", "z", "x", "z", "y"], "0110101110"], "56": [["y", "z", "z", "z", "z", "z", "x", "x", "y", "z"], "0000111001"], "57": [["x", "x", "z", "y", "y", "z", "x", "y", "y", "z"], "0011110010"], "58": [["x", "y", "z", "z", "x", "x", "x", "x", "y", "x"], "1001110000"], "59": [["x", "x", "z", "x", "z", "x", "x", "z", "x", "y"], "0100011001"], "60": [["z", "x", "x", "x", "z", "x", "x", "y", "y", "y"], "1010010010"], "61": [["y", "z", "z", "x", "y", "y", "y", "y", "z", "z"], "0110001000"], "62": [["y", "x", "y", "z", "x", "y", "x", "y", "z", "x"], "0111110110"], "63": [["x", "y", "y", "x", "z", "z", "x", "x", "y", "x"], "0111111100"], "64": [["y", "y", "z", "y", "x", "z", "y", "y", "z", "x"], "0110101000"], "65": [["x", "x", "x", "y", "y", "y", "x", "x", "z", "z"], "0101110001"], "66": [["x", "z", "y", "y", "y", "x", "y", "z", "z", "y"], "0101000000"], "67": [["y", "x", "x", "z", "y", "y", "z", "y", "y", "y"], "0101100100"], "68": [["x", "z", "x", "x", "x", "z", "x", "x", "x", "y"], "0100100001"], "69": [["y", "z", "y", "y", "z", "x", "x", "z", "x", "z"], "0101110001"], "70": [["z", "x", "y", "x", "x", "y", "y", "y", "x", "z"], "0000110100"], "71": [["z", "y", "y", "z", "z", "z", "y", "y", "z", "x"], "0101110110"], "72": [["x", "x", "z", "y", "x", "x", "y", "x", "x", "y"], "1110100010"], "73": [["y", "z", "x", "x", "y", "x", "z", "x", "x", "y"], "0001000101"], "74": [["y", "x", "z", "z", "x", "x", "y", "x", "z", "y"], "1110110010"], "75": [["y", "x", "y", "z", "x", "z", "z", "x", "y", "x"], "1011100101"], "76": [["y", "x", "z", "y", "x", "x", "z", "x", "z", "x"], "1111110001"], "77": [["z", "z", "y", "x", "y", "y", "z", "y", "z", "y"], "1111000100"], "78": [["z", "y", "y", "z", "z", "x", "x", "z", "y", "y"], "0101110110"], "79": [["y", "z", "x", "x", "y", "z", "x", "z", "x", "z"], "0101111100"], "80": [["y", "x", "x", "x", "y", "x", "x", "z", "z", "x"], "0101111010"], "81": [["x", "x", "x", "x", "x", "y", "y", "z", "z", "z"], "0101001000"], "82": [["z", "y", "x", "y", "z", "x", "z", "z", "y", "z"], "0101111100"], "83": [["y", "x", "y", "y", "x", "y", "y", "z", "z", "z"], "0100001101"], "84": [["x", "y", "x", "y", "x", "y", "x", "z", "x", "y"], "1001001011"], "85": [["z", "y", "y", "y", "z", "z", "y", "x", "z", "z"], "0100110010"], "86": [["z", "z", "x", "x", "y", "z", "y", "z", "z", "z"], "0100111100"], "87": [["y", "z", "z", "y", "x", "z", "z", "y", "z", "y"], "1101101000"], "88": [["y", "y", "x", "x", "x", "z", "z", "y", "z", "y"], "1101100101"], "89": [["z", "z", "x", "y", "x", "x", "x", "y", "z", "z"], "0111110000"], "90": [["y", "y", "y", "x", "x", "y", "y", "y", "z", "y"], "1100111011"], "91": [["x", "y", "x", "x", "x", "y", "y", "y", "x", "y"], "1011101001"], "92": [["x", "y", "x", "y", "x", "z", "y", "z", "x", "y"], "1101100000"], "93": [["y", "z", "x", "x", "x", "x", "z", "y", "z", "x"], "0101001100"], "94": [["x", "z", "y", "z", "y", "z", "y", "z", "y", "y"], "0000100001"], "95": [["z", "y", "z", "z", "x", "z", "z", "x", "y", "x"], "0001110010"], "96": [["x", "z", "y", "z", "x", "x", "y", "x", "y", "y"], "1111110100"], "97": [["z", "z", "x", "x", "x", "z", "z", "z", "x", "z"], "0101100100"], "98": [["z", "z", "x", "y", "x", "z", "y", "x", "y", "y"], "0010110100"], "99": [["x", "y", "x", "z", "z", "y", "x", "z", "y", "x"], "1101110101"], "100": [["x", "x", "x", "z", "x", "x", "x", "y", "x", "y"], "1010110000"], "101": [["z", "x", "y", "y", "z", "y", "z", "y", "z", "z"], "0101111000"], "102": [["z", "z", "x", "x", "x", "z", "y", "x", "x", "x"], "0101101000"], "103": [["z", "z", "z", "z", "y", "y", "x", "x", "y", "y"], "0001110000"], "104": [["z", "x", "x", "z", "y", "y", "y", "x", "x", "z"], "0001110000"], "105": [["x", "x", "z", "x", "y", "z", "z", "y", "z", "x"], "1111101010"], "106": [["z", "z", "x", "x", "z", "x", "x", "x", "x", "z"], "0000011000"], "107": [["x", "x", "z", "x", "x", "x", "z", "z", "x", "z"], "0101011000"], "108": [["x", "z", "x", "z", "x", "x", "y", "z", "y", "x"], "0001000101"], "109": [["y", "y", "z", "z", "x", "y", "z", "y", "x", "y"], "0001110010"], "110": [["x", "z", "x", "x", "x", "z", "y", "x", "z", "x"], "0110101000"], "111": [["y", "y", "z", "z", "x", "x", "x", "z", "y", "z"], "0101110011"], "112": [["y", "y", "z", "z", "x", "x", "x", "z", "y", "x"], "1001110011"], "113": [["z", "y", "x", "z", "y", "y", "z", "y", "x", "x"], "0111100000"], "114": [["x", "z", "z", "z", "x", "z", "x", "z", "x", "z"], "0000100001"], "115": [["z", "x", "x", "z", "z", "x", "y", "x", "x", "z"], "0010010010"], "116": [["y", "y", "x", "y", "z", "y", "y", "y", "x", "x"], "0110010011"], "117": [["y", "z", "x", "y", "y", "y", "z", "y", "x", "x"], "1111010101"], "118": [["x", "x", "z", "y", "x", "x", "x", "z", "x", "y"], "0001000011"], "119": [["x", "y", "z", "z", "y", "x", "x", "y", "x", "x"], "1110010011"], "120": [["z", "y", "x", "x", "x", "z", "z", "y", "y", "x"], "0011110110"], "121": [["y", "x", "x", "y", "x", "z", "y", "y", "x", "x"], "1110100001"], "122": [["y", "x", "z", "z", "y", "x", "z", "z", "x", "z"], "0001100001"], "123": [["x", "x", "y", "y", "x", "z", "y", "z", "x", "x"], "0000111011"], "124": [["z", "z", "z", "y", "y", "y", "z", "z", "y", "z"], "0101001000"], "125": [["z", "x", "z", "y", "y", "z", "y", "z", "y", "x"], "0100110010"], "126": [["x", "x", "x", "x", "z", "z", "y", "z", "z", "x"], "1100111110"], "127": [["y", "z", "z", "z", "z", "x", "x", "z", "x", "z"], "0100110000"], "128": [["y", "y", "z", "y", "y", "x", "x", "y", "x", "z"], "0001101001"], "129": [["x", "z", "y", "z", "x", "z", "y", "y", "y", "y"], "0010110101"], "130": [["y", "y", "x", "y", "y", "z", "y", "x", "z", "z"], "0110101010"], "131": [["z", "x", "x", "x", "x", "x", "x", "x", "z", "y"], "1101011110"], "132": [["x", "x", "x", "y", "z", "x", "y", "x", "z", "x"], "0100011000"], "133": [["z", "z", "z", "z", "x", "x", "y", "x", "z", "z"], "0111000000"], "134": [["y", "x", "y", "z", "z", "y", "y", "x", "x", "x"], "0000010111"], "135": [["z", "z", "y", "z", "x", "x", "x", "x", "y", "x"], "1010000000"], "136": [["x", "z", "y", "y", "x", "x", "y", "y", "y", "y"], "0111000100"], "137": [["x", "x", "z", "z", "x", "x", "x", "y", "x", "z"], "0000100011"], "138": [["z", "x", "x", "x", "x", "y", "x", "y", "x", "y"], "1111110110"], "139": [["x", "x", "y", "x", "z", "y", "y", "x", "x", "x"], "0101011101"], "140": [["y", "z", "z", "x", "x", "y", "z", "z", "x", "y"], "1101010001"], "141": [["x", "z", "z", "z", "z", "x", "z", "y", "z", "z"], "0111110000"], "142": [["x", "z", "x", "z", "z", "x", "x", "z", "z", "z"], "0101010100"], "143": [["x", "z", "z", "y", "x", "x", "z", "x", "z", "z"], "0111000000"], "144": [["y", "y", "z", "x", "x", "x", "x", "x", "z", "z"], "0111100001"], "145": [["y", "x", "y", "y", "z", "y", "z", "x", "x", "y"], "1001110101"], "146": [["x", "z", "y", "y", "y", "x", "z", "y", "x", "x"], "1101001101"], "147": [["y", "z", "z", "y", "y", "x", "x", "x", "x", "z"], "0000100001"], "148": [["x", "y", "x", "x", "z", "x", "x", "y", "z", "x"], "0110011101"], "149": [["y", "z", "z", "y", "y", "z", "x", "x", "y", "y"], "1010101000"], "150": [["y", "x", "y", "x", "y", "z", "z", "y", "z", "x"], "1111101000"], "151": [["y", "x", "z", "z", "y", "y", "x", "z", "z", "y"], "1110000110"], "152": [["z", "x", "z", "x", "z", "y", "y", "y", "z", "y"], "0101111010"], "153": [["y", "x", "y", "y", "x", "y", "x", "y", "z", "y"], "0101010100"], "154": [["y", "y", "x", "z", "x", "z", "z", "y", "y", "y"], "0011110011"], "155": [["y", "x", "y", "y", "x", "z", "z", "y", "z", "x"], "0101100100"], "156": [["x", "y", "y", "x", "x", "x", "z", "x", "y", "x"], "1001111011"], "157": [["x", "x", "x", "z", "y", "z", "z", "x", "z", "x"], "0111100000"], "158": [["y", "x", "z", "z", "x", "x", "y", "z", "x", "z"], "0000100010"], "159": [["x", "x", "z", "y", "x", "y", "x", "y", "z", "z"], "0111100001"], "160": [["y", "y", "x", "y", "y", "y", "x", "x", "z", "x"], "0100100101"], "161": [["z", "y", "z", "y", "z", "x", "z", "z", "x", "x"], "1001010000"], "162": [["x", "y", "z", "z", "z", "z", "z", "y", "y", "y"], "0001110001"], "163": [["z", "z", "x", "y", "y", "z", "z", "x", "x", "z"], "0001100000"], "164": [["y", "z", "x", "z", "x", "x", "z", "y", "x", "x"], "1011010000"], "165": [["x", "x", "y", "x", "y", "z", "z", "x", "z", "z"], "0101100000"], "166": [["x", "y", "z", "y", "z", "x", "z", "y", "y", "z"], "0011011011"], "167": [["x", "y", "z", "z", "z", "x", "y", "y", "x", "x"], "1000010010"], "168": [["z", "x", "z", "x", "z", "y", "x", "y", "x", "z"], "0000011010"], "169": [["z", "z", "y", "y", "y", "z", "x", "z", "z", "z"], "0101101000"], "170": [["z", "z", "x", "x", "y", "x", "x", "y", "y", "y"], "0101101000"], "171": [["x", "x", "x", "z", "z", "z", "z", "z", "y", "y"], "0001110110"], "172": [["x", "z", "x", "z", "z", "x", "y", "z", "x", "x"], "0000110001"], "173": [["y", "y", "z", "z", "x", "z", "x", "y", "y", "y"], "0011110010"], "174": [["x", "x", "z", "y", "x", "x", "z", "x", "z", "x"], "0111000001"], "175": [["x", "y", "y", "y", "x", "x", "x", "y", "z", "x"], "1101100000"], "176": [["x", "y", "y", "x", "x", "x", "z", "z", "y", "y"], "0101011011"], "177": [["z", "y", "x", "x", "x", "y", "x", "z", "z", "y"], "0101011100"], "178": [["z", "y", "y", "z", "y", "x", "x", "x", "x", "z"], "0101110110"], "179": [["z", "z", "x", "x", "y", "z", "y", "z", "y", "z"], "0101111000"], "180": [["x", "z", "z", "y", "y", "x", "x", "y", "x", "z"], "0100111000"], "181": [["z", "x", "z", "y", "z", "y", "x", "x", "x", "x"], "0111011000"], "182": [["z", "z", "y", "z", "z", "y", "z", "z", "z", "z"], "0101010100"], "183": [["y", "x", "y", "x", "z", "z", "y", "y", "y", "y"], "0111110011"], "184": [["y", "x", "z", "z", "x", "x", "x", "x", "x", "y"], "0000010001"], "185": [["x", "y", "x", "x", "z", "z", "z", "z", "z", "y"], "1101110110"], "186": [["y", "x", "z", "z", "y", "z", "y", "x", "z", "y"], "1101100011"], "187": [["y", "x", "y", "z", "y", "y", "y", "z", "z", "x"], "1100100011"], "188": [["z", "y", "y", "z", "z", "z", "y", "y", "y", "z"], "0011110000"], "189": [["z", "x", "y", "y", "z", "x", "x", "y", "x", "z"], "0000111010"], "190": [["x", "z", "z", "y", "y", "x", "y", "x", "z", "x"], "1100100000"], "191": [["x", "y", "z", "z", "y", "x", "x", "y", "x", "z"], "0001010000"], "192": [["x", "y", "x", "y", "x", "y", "y", "x", "z", "z"], "0100110011"], "193": [["y", "x", "y", "y", "z", "y", "x", "x", "z", "z"], "0111110111"], "194": [["z", "x", "z", "y", "y", "y", "y", "y", "y", "y"], "1000101010"], "195": [["y", "z", "z", "y", "y", "y", "x", "x", "y", "x"], "1101101001"], "196": [["x", "x", "z", "x", "z", "x", "y", "y", "x", "x"], "0001110000"], "197": [["x", "y", "y", "x", "x", "y", "x", "y", "y", "z"], "0100010011"], "198": [["x", "z", "z", "z", "x", "z", "y", "y", "x", "x"], "0010100000"], "199": [["x", "y", "x", "x", "x", "z", "y", "x", "z", "x"], "1101110000"], "200": [["x", "y", "x", "y", "x", "z", "x", "z", "y", "z"], "0100111010"], "201": [["x", "z", "y", "z", "z", "y", "x", "y", "x", "z"], "0110110101"], "202": [["y", "y", "x", "z", "y", "z", "y", "x", "y", "z"], "0101100110"], "203": [["y", "z", "z", "z", "z", "z", "y", "z", "y", "z"], "0101110001"], "204": [["y", "y", "y", "z", "y", "y", "x", "x", "z", "y"], "0100000011"], "205": [["x", "y", "z", "x", "x", "y", "x", "y", "x", "y"], "1010110001"], "206": [["y", "z", "y", "y", "z", "y", "x", "z", "y", "x"], "1101011001"], "207": [["z", "y", "x", "z", "x", "y", "y", "y", "x", "x"], "1001010000"], "208": [["x", "y", "y", "y", "x", "z", "z", "x", "z", "z"], "0101100010"], "209": [["y", "x", "x", "y", "z", "y", "x", "y", "x", "y"], "1101010101"], "210": [["z", "z", "x", "x", "x", "y", "z", "z", "y", "x"], "1101010000"], "211": [["x", "y", "z", "z", "y", "y", "y", "y", "y", "x"], "1110000010"], "212": [["y", "y", "x", "z", "z", "y", "y", "y", "z", "z"], "0101010111"], "213": [["x", "x", "z", "y", "z", "y", "y", "z", "y", "y"], "1000110001"], "214": [["z", "y", "z", "z", "x", "z", "x", "x", "x", "x"], "1100110000"], "215": [["x", "z", "x", "z", "y", "x", "x", "x", "y", "x"], "0001100100"], "216": [["x", "z", "y", "y", "x", "y", "y", "y", "z", "y"], "1101100000"], "217": [["x", "x", "z", "x", "z", "y", "y", "x", "z", "x"], "1111110000"], "218": [["x", "z", "z", "z", "y", "y", "y", "z", "z", "x"], "1101100000"], "219": [["x", "y", "y", "z", "x", "x", "x", "z", "z", "z"], "0100110111"], "220": [["x", "y", "z", "z", "z", "x", "z", "y", "z", "y"], "1101010001"], "221": [["z", "z", "y", "z", "z", "x", "x", "z", "z", "y"], "1100010100"], "222": [["x", "x", "y", "x", "y", "y", "z", "y", "x", "x"], "0001101011"], "223": [["z", "x", "x", "y", "x", "x", "x", "x", "x", "x"], "1100011110"], "224": [["z", "y", "x", "y", "z", "x", "x", "y", "y", "y"], "1101111110"], "225": [["x", "x", "y", "x", "x", "x", "z", "y", "y", "y"], "1011101111"], "226": [["x", "y", "z", "z", "y", "z", "z", "x", "z", "y"], "0111100011"], "227": [["y", "x", "y", "y", "y", "z", "z", "z", "y", "z"], "0101100001"], "228": [["x", "y", "x", "y", "x", "z", "x", "z", "z", "y"], "0101100101"], "229": [["y", "y", "x", "y", "z", "y", "x", "x", "x", "z"], "0010010111"], "230": [["y", "z", "z", "z", "x", "z", "y", "y", "z", "x"], "0100110001"], "231": [["y", "x", "x", "y", "z", "z", "x", "x", "y", "z"], "0110110101"], "232": [["y", "y", "y", "z", "y", "y", "x", "z", "y", "x"], "1101110111"], "233": [["z", "z", "x", "z", "z", "z", "z", "y", "z", "z"], "0101110100"], "234": [["y", "x", "y", "x", "x", "z", "z", "z", "y", "z"], "0101111100"], "235": [["y", "z", "y", "y", "x", "y", "z", "z", "y", "x"], "1101011101"], "236": [["y", "z", "z", "z", "x", "z", "y", "y", "x", "z"], "0110110001"], "237": [["y", "z", "z", "z", "x", "x", "z", "x", "z", "y"], "0101000001"], "238": [["x", "y", "z", "y", "z", "x", "y", "z", "z", "x"], "0100110001"], "239": [["z", "x", "z", "x", "y", "z", "y", "y", "z", "y"], "0110110000"], "240": [["x", "z", "x", "x", "z", "x", "y", "z", "y", "y"], "1001011100"], "241": [["x", "y", "x", "z", "y", "y", "y", "z", "x", "y"], "0100000101"], "242": [["z", "x", "z", "x", "y", "x", "y", "x", "y", "z"], "0111000000"], "243": [["z", "x", "x", "z", "y", "x", "y", "x", "x", "x"], "1110010100"], "244": [["y", "x", "x", "z", "y", "y", "y", "y", "x", "z"], "0011010101"], "245": [["z", "z", "x", "y", "y", "z", "x", "z", "z", "y"], "0100110000"], "246": [["x", "x", "x", "x", "x", "x", "x", "y", "z", "z"], "0100101011"], "247": [["z", "z", "x", "y", "z", "x", "x", "y", "x", "y"], "0001110000"], "248": [["y", "x", "z", "y", "y", "x", "y", "z", "x", "z"], "0001000010"], "249": [["y", "z", "z", "y", "z", "x", "x", "y", "y", "y"], "1010111001"], "250": [["y", "x", "x", "x", "z", "z", "y", "y", "x", "z"], "0111110100"], "251": [["x", "x", "y", "x", "x", "x", "x", "z", "x", "x"], "0001010111"], "252": [["x", "x", "y", "x", "z", "x", "z", "x", "x", "z"], "0001110001"], "253": [["x", "z", "x", "x", "y", "y", "y", "y", "y", "x"], "0011100000"], "254": [["y", "z", "z", "z", "z", "z", "y", "x", "z", "y"], "1101110001"], "255": [["z", "x", "x", "z", "y", "x", "y", "y", "x", "z"], "0001000100"], "256": [["y", "z", "y", "y", "x", "x", "y", "x", "x", "z"], "0011011001"], "257": [["z", "x", "y", "x", "x", "z", "z", "z", "y", "y"], "1101110110"], "258": [["x", "y", "y", "x", "z", "y", "y", "z", "z", "y"], "1100110110"], "259": [["y", "x", "z", "y", "x", "z", "z", "y", "x", "z"], "0001101001"], "260": [["z", "z", "z", "y", "x", "y", "z", "x", "x", "z"], "0101100000"], "261": [["x", "z", "x", "x", "z", "y", "x", "y", "y", "z"], "0011111100"], "262": [["z", "z", "y", "x", "z", "z", "x", "z", "z", "y"], "1101111000"], "263": [["z", "x", "y", "x", "y", "x", "x", "x", "z", "x"], "0110101000"], "264": [["y", "x", "y", "x", "z", "x", "x", "x", "z", "y"], "1100011010"], "265": [["x", "x", "z", "z", "z", "z", "y", "y", "z", "x"], "0111110000"], "266": [["y", "y", "z", "y", "y", "x", "z", "y", "y", "z"], "0011000001"], "267": [["x", "x", "z", "z", "y", "z", "y", "z", "y", "x"], "1100110010"], "268": [["z", "y", "z", "y", "y", "y", "y", "z", "x", "z"], "0000000000"], "269": [["x", "y", "z", "z", "z", "x", "y", "z", "z", "x"], "1101010011"], "270": [["y", "y", "z", "x", "z", "y", "x", "z", "x", "y"], "1101011011"], "271": [["y", "x", "y", "x", "z", "y", "z", "y", "z", "y"], "0101011100"], "272": [["z", "y", "x", "y", "y", "z", "y", "z", "x", "y"], "0100100110"], "273": [["y", "x", "x", "z", "y", "y", "x", "z", "y", "z"], "0000110110"], "274": [["z", "y", "y", "y", "x", "y", "y", "z", "z", "z"], "0100011010"], "275": [["x", "y", "x", "x", "y", "y", "z", "y", "x", "y"], "0001001001"], "276": [["x", "x", "x", "z", "x", "y", "y", "y", "y", "z"], "0010110101"], "277": [["x", "y", "x", "y", "y", "z", "x", "x", "z", "z"], "0111110011"], "278": [["y", "z", "x", "z", "y", "z", "x", "z", "y", "x"], "1000110101"], "279": [["x", "x", "y", "y", "y", "y", "y", "x", "x", "x"], "0000100000"], "280": [["x", "z", "x", "x", "y", "y", "z", "x", "z", "y"], "1111110100"], "281": [["x", "y", "z", "y", "x", "y", "x", "z", "z", "z"], "0100110001"], "282": [["x", "y", "y", "z", "x", "z", "z", "z", "y", "x"], "1001100101"], "283": [["z", "z", "x", "x", "z", "y", "z", "x", "z", "x"], "1101110100"], "284": [["z", "x", "y", "x", "y", "y", "z", "x", "y", "x"], "0111101100"], "285": [["x", "x", "y", "z", "y", "z", "y", "x", "z", "x"], "1111100100"], "286": [["x", "y", "y", "y", "x", "z", "y", "z", "z", "y"], "1101101110"], "287": [["x", "y", "x", "y", "x", "z", "y", "z", "x", "x"], "0101110101"], "288": [["x", "z", "z", "z", "y", "x", "y", "x", "z", "x"], "1101100000"], "289": [["x", "y", "z", "y", "z", "x", "z", "x", "x", "z"], "0111010010"], "290": [["x", "x", "z", "z", "z", "x", "z", "z", "x", "x"], "0101110000"], "291": [["x", "x", "z", "z", "z", "z", "z", "z", "x", "z"], "0001110001"], "292": [["x", "y", "y", "y", "y", "x", "y", "z", "y", "x"], "1100100111"], "293": [["z", "z", "x", "x", "x", "y", "x", "z", "z", "z"], "0100100000"], "294": [["y", "x", "z", "z", "y", "y", "z", "x", "x", "x"], "0111100011"], "295": [["y", "y", "x", "x", "z", "y", "z", "y", "x", "x"], "1001011001"], "296": [["x", "z", "x", "y", "x", "z", "y", "x", "z", "z"], "0110101101"], "297": [["x", "z", "x", "x", "y", "y", "x", "x", "y", "z"], "0100000100"], "298": [["z", "z", "z", "z", "y", "z", "x", "y", "y", "y"], "0100110000"], "299": [["x", "z", "y", "z", "y", "z", "z", "y", "z", "x"], "0111110001"], "300": [["x", "z", "z", "x", "x", "z", "x", "z", "x", "x"], "0001111000"], "301": [["z", "z", "x", "x", "z", "x", "z", "x", "z", "x"], "0101110000"], "302": [["z", "x", "y", "z", "z", "z", "y", "y", "z", "x"], "1110110110"], "303": [["z", "y", "x", "x", "y", "y", "x", "z", "x", "y"], "0001010100"], "304": [["x", "x", "z", "z", "y", "x", "y", "x", "z", "z"], "0101100001"], "305": [["x", "y", "x", "x", "x", "y", "y", "y", "x", "z"], "0100000010"], "306": [["z", "x", "x", "y", "z", "z", "z", "z", "y", "z"], "0101110110"], "307": [["y", "x", "z", "z", "x", "x", "x", "x", "y", "y"], "1110010000"], "308": [["z", "z", "z", "z", "y", "z", "y", "y", "z", "z"], "0110110000"], "309": [["y", "z", "z", "z", "z", "x", "y", "y", "y", "z"], "0110110000"], "310": [["z", "z", "y", "y", "y", "y", "y", "x", "x", "z"], "0101011000"], "311": [["x", "y", "x", "z", "y", "x", "z", "y", "x", "z"], "0001100000"], "312": [["y", "z", "z", "x", "x", "y", "x", "x", "z", "x"], "1110111001"], "313": [["x", "y", "x", "z", "x", "x", "y", "y", "y", "y"], "0111110010"], "314": [["x", "z", "x", "x", "x", "z", "z", "y", "x", "z"], "0101110101"], "315": [["z", "y", "z", "x", "z", "x", "y", "y", "x", "z"], "0001010111"], "316": [["x", "y", "y", "z", "z", "y", "y", "y", "x", "x"], "1111010101"], "317": [["z", "y", "y", "y", "y", "z", "y", "z", "y", "z"], "0100111010"], "318": [["z", "x", "y", "y", "y", "y", "z", "x", "x", "y"], "0111110010"], "319": [["z", "y", "x", "x", "x", "y", "x", "x", "x", "y"], "0100000010"], "320": [["z", "z", "x", "y", "z", "z", "y", "z", "z", "y"], "1101111000"], "321": [["y", "y", "y", "z", "x", "x", "z", "x", "x", "y"], "1111110110"], "322": [["y", "x", "y", "x", "z", "z", "x", "x", "x", "z"], "0001111101"], "323": [["x", "y", "x", "y", "x", "x", "z", "z", "y", "y"], "1101011101"], "324": [["x", "y", "z", "z", "y", "z", "z", "y", "y", "x"], "0001100011"], "325": [["z", "z", "x", "y", "y", "z", "z", "x", "y", "y"], "0011101000"], "326": [["x", "z", "y", "z", "x", "y", "z", "y", "y", "y"], "1001000101"], "327": [["x", "x", "x", "x", "z", "x", "x", "y", "x", "x"], "1101111001"], "328": [["z", "y", "x", "x", "y", "z", "x", "z", "x", "y"], "0100110010"], "329": [["x", "x", "x", "x", "z", "z", "y", "x", "z", "x"], "1111110100"], "330": [["y", "y", "x", "z", "z", "x", "x", "x", "x", "x"], "0000110100"], "331": [["x", "x", "z", "y", "y", "z", "y", "x", "x", "z"], "0001111011"], "332": [["y", "y", "z", "y", "y", "y", "z", "z", "z", "y"], "1101011000"], "333": [["z", "z", "z", "x", "z", "x", "x", "y", "z", "z"], "0100111000"], "334": [["y", "x", "z", "z", "y", "x", "x", "z", "y", "x"], "1001100010"], "335": [["x", "y", "z", "y", "x", "x", "y", "x", "y", "x"], "1000011011"], "336": [["z", "x", "x", "x", "y", "z", "y", "z", "y", "y"], "1100110000"], "337": [["y", "y", "z", "y", "x", "y", "y", "x", "x", "x"], "0011001010"], "338": [["x", "y", "x", "x", "x", "z", "y", "x", "z", "x"], "1110101011"], "339": [["z", "z", "y", "y", "z", "z", "z", "z", "y", "y"], "1001110100"], "340": [["z", "z", "x", "x", "z", "z", "z", "x", "z", "y"], "0111111100"], "341": [["y", "x", "z", "x", "y", "z", "z", "z", "x", "z"], "0101100010"], "342": [["y", "x", "y", "x", "y", "x", "x", "y", "x", "z"], "0111110011"], "343": [["y", "y", "x", "x", "x", "z", "z", "y", "x", "y"], "0011101000"], "344": [["y", "y", "y", "z", "x", "x", "x", "z", "x", "y"], "0101110100"], "345": [["x", "z", "z", "z", "x", "z", "y", "y", "z", "y"], "1111100000"], "346": [["x", "z", "x", "z", "y", "z", "z", "z", "x", "z"], "0101110100"], "347": [["x", "y", "z", "z", "y", "y", "z", "x", "x", "z"], "0101110010"], "348": [["y", "z", "y", "y", "y", "z", "y", "z", "y", "x"], "1001100001"], "349": [["y", "y", "y", "x", "x", "z", "x", "x", "y", "z"], "0001100101"], "350": [["z", "z", "x", "z", "z", "z", "y", "z", "y", "z"], "0100110000"], "351": [["y", "x", "z", "z", "x", "y", "z", "z", "x", "y"], "1001000001"], "352": [["y", "y", "x", "y", "y", "z", "y", "z", "y", "x"], "1100111100"], "353": [["y", "y", "x", "y", "y", "y", "x", "z", "z", "x"], "0101110011"], "354": [["y", "x", "y", "x", "x", "y", "y", "z", "y", "z"], "0000011110"], "355": [["y", "y", "y", "x", "x", "z", "x", "x", "x", "y"], "0010111111"], "356": [["x", "x", "z", "z", "z", "y", "y", "x", "x", "y"], "1110110001"], "357": [["y", "y", "y", "x", "z", "x", "x", "z", "y", "y"], "0101110000"], "358": [["y", "y", "z", "z", "y", "z", "z", "z", "y", "z"], "0101100000"], "359": [["x", "y", "y", "y", "y", "z", "y", "x", "x", "y"], "0000110011"], "360": [["y", "x", "y", "x", "x", "z", "x", "y", "y", "z"], "0110110001"], "361": [["z", "x", "z", "x", "z", "x", "z", "x", "z", "y"], "0111011010"], "362": [["z", "z", "y", "z", "z", "z", "x", "x", "z", "x"], "1101110100"], "363": [["x", "y", "y", "y", "x", "y", "y", "z", "x", "z"], "0000111110"], "364": [["y", "y", "y", "x", "y", "x", "x", "y", "x", "y"], "0001011110"], "365": [["y", "y", "z", "z", "z", "z", "z", "z", "z", "x"], "0101110011"], "366": [["z", "x", "x", "z", "y", "y", "z", "y", "z", "z"], "0111000000"], "367": [["x", "z", "y", "x", "x", "x", "y", "z", "z", "z"], "0100011100"], "368": [["x", "y", "x", "x", "z", "x", "z", "z", "x", "x"], "0101010000"], "369": [["z", "z", "z", "z", "y", "x", "z", "y", "z", "z"], "0111000000"], "370": [["x", "z", "z", "z", "z", "z", "y", "x", "y", "x"], "0000110001"], "371": [["x", "y", "x", "x", "z", "y", "z", "x", "x", "x"], "1111111101"], "372": [["y", "y", "x", "y", "x", "y", "x", "x", "x", "z"], "0010111000"], "373": [["x", "y", "y", "x", "z", "y", "x", "y", "y", "x"], "1100011100"], "374": [["x", "z", "y", "z", "y", "y", "y", "z", "y", "x"], "1001010101"], "375": [["x", "x", "x", "y", "y", "x", "x", "x", "y", "y"], "1001111101"], "376": [["z", "y", "x", "y", "x", "y", "x", "z", "z", "x"], "0100101000"], "377": [["y", "x", "z", "z", "x", "y", "z", "y", "x", "x"], "1011110001"], "378": [["x", "x", "x", "z", "x", "z", "y", "x", "z", "z"], "0110110010"], "379": [["x", "y", "z", "z", "z", "x", "z", "x", "x", "z"], "0001010001"], "380": [["y", "y", "y", "x", "x", "y", "y", "y", "x", "y"], "1100100011"], "381": [["x", "x", "z", "y", "z", "y", "x", "x", "z", "x"], "1111010010"], "382": [["y", "y", "y", "z", "z", "x", "z", "y", "z", "x"], "0101110011"], "383": [["y", "y", "y", "z", "x", "y", "y", "x", "z", "y"], "0110110111"], "384": [["z", "z", "z", "z", "z", "x", "x", "x", "x", "y"], "0110110000"], "385": [["x", "z", "z", "y", "z", "z", "z", "x", "z", "z"], "0101111001"], "386": [["x", "z", "z", "x", "x", "y", "z", "z", "z", "y"], "0101011000"], "387": [["y", "y", "y", "x", "x", "x", "y", "x", "y", "x"], "1011001101"], "388": [["y", "y", "y", "x", "z", "y", "z", "x", "x", "z"], "0001110100"], "389": [["z", "y", "z", "y", "y", "z", "y", "x", "y", "y"], "1100101010"], "390": [["x", "z", "x", "x", "x", "x", "z", "z", "x", "y"], "0001101100"], "391": [["y", "z", "y", "z", "y", "y", "x", "y", "z", "y"], "0111001001"], "392": [["z", "z", "x", "x", "x", "z", "z", "y", "x", "y"], "1111110100"], "393": [["z", "y", "x", "z", "x", "y", "y", "z", "z", "z"], "0101110100"], "394": [["z", "y", "z", "z", "x", "y", "z", "y", "x", "x"], "1111000000"], "395": [["y", "x", "z", "z", "y", "z", "y", "y", "z", "y"], "0110100000"], "396": [["z", "x", "x", "x", "x", "y", "x", "x", "x", "y"], "1000110000"], "397": [["y", "y", "x", "y", "z", "x", "z", "x", "y", "x"], "1011011101"], "398": [["x", "y", "z", "y", "x", "z", "z", "y", "y", "z"], "0011100010"], "399": [["y", "x", "y", "y", "x", "y", "y", "z", "x", "y"], "0100010111"], "400": [["z", "z", "x", "x", "x", "z", "y", "z", "y", "z"], "0100101000"], "401": [["y", "x", "y", "y", "x", "z", "x", "x", "x", "y"], "1100100100"], "402": [["z", "z", "y", "y", "z", "x", "y", "x", "z", "x"], "0110010000"], "403": [["x", "y", "x", "x", "y", "x", "x", "z", "x", "x"], "1101101011"], "404": [["y", "z", "x", "x", "y", "z", "z", "y", "z", "y"], "1101111101"], "405": [["z", "y", "z", "y", "y", "x", "z", "x", "z", "y"], "1101010000"], "406": [["y", "x", "z", "x", "y", "y", "x", "z", "x", "z"], "0101110010"], "407": [["y", "z", "y", "z", "y", "z", "y", "x", "y", "x"], "1100100100"], "408": [["x", "x", "x", "y", "x", "x", "z", "z", "z", "z"], "0100000011"], "409": [["z", "z", "y", "x", "x", "z", "z", "y", "z", "y"], "0101101100"], "410": [["x", "z", "x", "z", "z", "y", "y", "x", "z", "z"], "0100010001"], "411": [["x", "x", "x", "z", "y", "y", "x", "x", "x", "x"], "1100001101"], "412": [["z", "y", "x", "y", "z", "y", "y", "x", "z", "x"], "0101010000"], "413": [["y", "x", "y", "x", "z", "z", "y", "x", "y", "y"], "1100111000"], "414": [["x", "y", "y", "x", "y", "y", "y", "x", "y", "z"], "0111111111"], "415": [["x", "y", "z", "x", "x", "x", "y", "z", "z", "x"], "0101101000"], "416": [["y", "z", "z", "x", "y", "x", "z", "y", "x", "x"], "0011110001"], "417": [["y", "y", "x", "z", "z", "x", "x", "x", "z", "z"], "0101110100"], "418": [["y", "x", "x", "y", "y", "y", "z", "z", "z", "z"], "0101001100"], "419": [["x", "x", "z", "x", "z", "y", "y", "z", "x", "x"], "0100111011"], "420": [["y", "z", "y", "y", "z", "y", "x", "z", "y", "y"], "0001110001"], "421": [["x", "z", "y", "z", "y", "z", "y", "z", "z", "y"], "0101100101"], "422": [["z", "x", "y", "y", "x", "y", "x", "x", "z", "y"], "1111101110"], "423": [["z", "x", "z", "x", "z", "x", "x", "y", "y", "y"], "0110111010"], "424": [["z", "x", "z", "x", "y", "z", "y", "z", "y", "x"], "0000110010"], "425": [["x", "x", "x", "z", "z", "y", "z", "x", "y", "y"], "1001010001"], "426": [["z", "z", "y", "x", "z", "z", "z", "x", "z", "z"], "0111110100"], "427": [["y", "z", "z", "x", "z", "z", "x", "y", "z", "x"], "1110111001"], "428": [["y", "z", "x", "x", "z", "z", "y", "z", "x", "z"], "0000111100"], "429": [["y", "z", "y", "z", "z", "z", "x", "z", "x", "z"], "0101110101"], "430": [["y", "z", "z", "y", "z", "z", "z", "y", "x", "x"], "1011111001"], "431": [["z", "z", "y", "x", "z", "z", "x", "y", "z", "x"], "0110111000"], "432": [["x", "x", "y", "y", "y", "y", "x", "z", "z", "y"], "1100011001"], "433": [["z", "y", "y", "y", "x", "z", "y", "x", "z", "x"], "1101100000"], "434": [["y", "x", "y", "z", "x", "y", "z", "x", "z", "z"], "0101100001"], "435": [["y", "y", "z", "z", "y", "z", "y", "y", "y", "x"], "1110100001"], "436": [["z", "y", "z", "y", "x", "z", "y", "y", "z", "x"], "0101100010"], "437": [["x", "y", "z", "z", "y", "x", "z", "x", "y", "x"], "0011110010"], "438": [["z", "z", "y", "y", "x", "z", "z", "x", "z", "z"], "0111101100"], "439": [["y", "x", "y", "y", "x", "z", "x", "y", "y", "x"], "1001101100"], "440": [["z", "y", "y", "x", "y", "x", "x", "z", "x", "x"], "1101011000"], "441": [["z", "x", "z", "z", "z", "x", "y", "x", "x", "z"], "0100010010"], "442": [["y", "x", "y", "y", "z", "x", "z", "y", "y", "x"], "1101010100"], "443": [["x", "y", "z", "y", "z", "x", "x", "y", "z", "z"], "0110110000"], "444": [["y", "z", "x", "z", "y", "x", "x", "z", "x", "z"], "0100010001"], "445": [["z", "y", "x", "z", "z", "z", "x", "z", "x", "z"], "0000110000"], "446": [["z", "x", "x", "y", "z", "x", "x", "z", "x", "x"], "0100011010"], "447": [["y", "z", "z", "x", "x", "x", "y", "x", "z", "y"], "1101010000"], "448": [["z", "y", "z", "y", "x", "x", "x", "z", "z", "x"], "0100010010"], "449": [["x", "z", "x", "z", "z", "x", "z", "z", "y", "y"], "0101110001"], "450": [["z", "z", "y", "z", "z", "y", "y", "y", "x", "x"], "0011110000"], "451": [["z", "y", "x", "y", "y", "y", "z", "x", "y", "x"], "0001010000"], "452": [["x", "z", "y", "y", "x", "y", "y", "z", "y", "y"], "0000111101"], "453": [["x", "y", "z", "z", "x", "z", "z", "y", "y", "x"], "0011110000"], "454": [["x", "y", "x", "y", "y", "x", "z", "z", "x", "z"], "0101111001"], "455": [["y", "x", "y", "z", "y", "z", "z", "y", "x", "x"], "0101110000"], "456": [["z", "z", "z", "z", "x", "y", "x", "y", "x", "y"], "0101100000"], "457": [["y", "x", "y", "y", "z", "x", "x", "z", "y", "x"], "0101011111"], "458": [["y", "z", "x", "z", "x", "y", "y", "z", "z", "y"], "1100010101"], "459": [["z", "x", "z", "x", "y", "z", "z", "z", "x", "y"], "1001111010"], "460": [["z", "y", "z", "y", "y", "y", "x", "y", "y", "x"], "0101011010"], "461": [["y", "x", "z", "x", "z", "z", "y", "y", "z", "x"], "0111111010"], "462": [["x", "z", "x", "z", "y", "y", "z", "x", "y", "z"], "0111110100"], "463": [["x", "z", "y", "y", "z", "z", "y", "y", "z", "x"], "1101110000"], "464": [["x", "z", "y", "y", "z", "z", "x", "x", "x", "z"], "0101111100"], "465": [["y", "y", "z", "z", "y", "z", "y", "x", "x", "z"], "0111100001"], "466": [["y", "y", "y", "z", "x", "y", "z", "y", "x", "y"], "0001000100"], "467": [["y", "z", "x", "x", "z", "z", "z", "z", "y", "x"], "0101110101"], "468": [["y", "z", "z", "x", "y", "x", "z", "y", "z", "x"], "1101011000"], "469": [["z", "y", "z", "x", "z", "y", "z", "z", "x", "y"], "0001110010"], "470": [["y", "x", "y", "z", "z", "x", "z", "x", "z", "x"], "0111010110"], "471": [["y", "z", "x", "x", "z", "z", "y", "x", "z", "y"], "0100111101"], "472": [["y", "x", "z", "z", "y", "y", "z", "x", "y", "x"], "0011010001"], "473": [["z", "x", "y", "x", "y", "z", "x", "z", "y", "y"], "0101100000"], "474": [["z", "x", "z", "z", "z", "z", "y", "z", "x", "y"], "1001110010"], "475": [["x", "y", "y", "z", "z", "y", "y", "x", "y", "x"], "1101110100"], "476": [["z", "x", "y", "x", "z", "z", "z", "y", "x", "x"], "1111111110"], "477": [["x", "z", "z", "x", "y", "z", "x", "x", "z", "y"], "0110111000"], "478": [["y", "x", "x", "y", "x", "z", "x", "x", "x", "y"], "1001110000"], "479": [["y", "z", "z", "y", "z", "y", "z", "y", "z", "x"], "0111110001"], "480": [["y", "x", "z", "z", "y", "z", "y", "z", "z", "y"], "1101110010"], "481": [["x", "x", "x", "y", "x", "x", "z", "x", "y", "y"], "0111101110"], "482": [["x", "x", "x", "z", "y", "z", "x", "y", "z", "z"], "0100100111"], "483": [["z", "y", "y", "z", "z", "z", "y", "z", "z", "y"], "1100110100"], "484": [["x", "z", "z", "z", "x", "z", "y", "x", "x", "x"], "0001100001"], "485": [["x", "y", "z", "y", "x", "y", "y", "x", "z", "z"], "0101010000"], "486": [["x", "x", "z", "z", "y", "y", "z", "z", "x", "x"], "0001110001"], "487": [["z", "z", "z", "z", "y", "y", "x", "z", "z", "z"], "0101010000"], "488": [["z", "y", "y", "x", "y", "z", "x", "x", "x", "x"], "0000110100"], "489": [["z", "x", "z", "x", "y", "z", "x", "z", "y", "x"], "1101100000"], "490": [["y", "x", "y", "x", "z", "z", "y", "x", "x", "z"], "0000110101"], "491": [["x", "z", "z", "y", "y", "y", "z", "x", "x", "z"], "0111001000"], "492": [["y", "y", "y", "x", "x", "z", "x", "y", "x", "y"], "1010110001"], "493": [["y", "y", "x", "z", "z", "y", "x", "z", "x", "z"], "0001110011"], "494": [["x", "z", "y", "z", "z", "x", "y", "z", "y", "y"], "0100010000"], "495": [["z", "z", "z", "y", "z", "y", "x", "y", "x", "x"], "1010010010"], "496": [["y", "x", "x", "x", "y", "x", "z", "y", "x", "x"], "1001110000"], "497": [["y", "y", "y", "z", "z", "x", "z", "y", "z", "y"], "0111110111"], "498": [["x", "x", "z", "x", "z", "z", "z", "x", "y", "x"], "1101110001"], "499": [["y", "z", "y", "y", "z", "z", "y", "x", "z", "z"], "0101110001"], "500": [["z", "x", "z", "z", "y", "y", "x", "x", "y", "x"], "0101110000"], "501": [["y", "z", "y", "z", "y", "z", "z", "z", "y", "y"], "1001110001"], "502": [["z", "y", "y", "z", "x", "y", "y", "y", "x", "y"], "1101100010"], "503": [["z", "y", "y", "x", "x", "y", "z", "y", "x", "y"], "1001111000"], "504": [["z", "y", "x", "z", "z", "x", "y", "z", "x", "y"], "1100110100"], "505": [["y", "z", "x", "z", "x", "z", "z", "x", "x", "x"], "1001100101"], "506": [["x", "z", "y", "x", "z", "x", "y", "x", "x", "y"], "0001110001"], "507": [["y", "x", "z", "z", "z", "x", "z", "y", "z", "z"], "0101110011"], "508": [["y", "y", "x", "y", "x", "x", "z", "x", "y", "x"], "1101110000"], "509": [["y", "x", "z", "y", "y", "z", "y", "y", "z", "y"], "1100100010"], "510": [["x", "y", "x", "z", "x", "y", "y", "z", "y", "x"], "0101110001"], "511": [["y", "z", "x", "y", "y", "y", "y", "x", "x", "x"], "0011000001"], "512": [["y", "x", "z", "z", "y", "z", "z", "x", "x", "x"], "0011110001"], "513": [["y", "z", "x", "x", "x", "x", "z", "z", "x", "z"], "0001101100"], "514": [["y", "x", "x", "y", "z", "y", "z", "z", "x", "z"], "0101011110"], "515": [["z", "x", "x", "z", "y", "z", "y", "z", "z", "z"], "0101110010"], "516": [["x", "y", "x", "y", "y", "x", "y", "z", "y", "z"], "0101010011"], "517": [["y", "z", "y", "z", "y", "x", "y", "y", "y", "x"], "0100000100"], "518": [["y", "z", "z", "x", "x", "x", "z", "y", "y", "x"], "0011101000"], "519": [["y", "y", "z", "x", "y", "z", "x", "x", "x", "y"], "1111110000"], "520": [["y", "x", "x", "z", "z", "z", "y", "x", "z", "x"], "0110110111"], "521": [["x", "y", "x", "z", "z", "z", "z", "z", "y", "z"], "0001110010"], "522": [["x", "y", "z", "z", "z", "x", "y", "x", "z", "y"], "1101010010"], "523": [["y", "z", "y", "y", "z", "z", "z", "x", "z", "z"], "0111110001"], "524": [["z", "z", "y", "z", "z", "x", "y", "z", "z", "z"], "0100010000"], "525": [["z", "x", "z", "y", "z", "x", "z", "x", "x", "z"], "0001011010"], "526": [["y", "y", "x", "x", "z", "x", "z", "z", "z", "z"], "0101111011"], "527": [["z", "z", "y", "x", "x", "x", "x", "z", "z", "z"], "0101011000"], "528": [["x", "x", "y", "z", "x", "x", "x", "z", "x", "z"], "0001110101"], "529": [["z", "x", "z", "y", "x", "y", "z", "z", "y", "x"], "0001001010"], "530": [["z", "x", "x", "x", "z", "x", "z", "y", "y", "x"], "1001110000"], "531": [["y", "x", "x", "x", "z", "z", "y", "z", "y", "x"], "0000110000"], "532": [["z", "z", "y", "y", "y", "x", "z", "y", "x", "z"], "0111010000"], "533": [["y", "z", "x", "z", "y", "z", "z", "y", "z", "z"], "0110101000"], "534": [["y", "z", "y", "x", "z", "y", "x", "z", "x", "x"], "1000010000"], "535": [["y", "x", "x", "x", "y", "x", "y", "z", "x", "x"], "1001010001"], "536": [["x", "y", "x", "x", "y", "y", "z", "x", "z", "z"], "0101100111"], "537": [["y", "x", "x", "x", "y", "z", "x", "y", "z", "y"], "0111101100"], "538": [["x", "x", "x", "y", "y", "z", "x", "x", "x", "x"], "0100100011"], "539": [["z", "y", "x", "y", "x", "y", "y", "z", "x", "z"], "0100010010"], "540": [["x", "x", "y", "z", "z", "y", "y", "y", "x", "y"], "1111010100"], "541": [["y", "x", "z", "z", "z", "x", "x", "z", "z", "z"], "0101110000"], "542": [["x", "z", "x", "x", "x", "z", "y", "y", "x", "y"], "0000111000"], "543": [["y", "x", "z", "x", "z", "z", "y", "z", "y", "y"], "1000110000"], "544": [["x", "x", "z", "y", "x", "x", "x", "x", "x", "z"], "0110111010"], "545": [["x", "y", "x", "x", "x", "y", "x", "y", "y", "z"], "0110110111"], "546": [["x", "x", "y", "x", "y", "x", "y", "y", "y", "z"], "0010111111"], "547": [["y", "y", "z", "y", "x", "y", "x", "x", "x", "z"], "0101111001"], "548": [["z", "z", "z", "x", "x", "y", "y", "z", "y", "y"], "0000100000"], "549": [["x", "x", "y", "z", "z", "x", "y", "y", "y", "y"], "1110110111"], "550": [["z", "x", "x", "z", "z", "x", "y", "z", "x", "y"], "0101110000"], "551": [["z", "y", "y", "z", "z", "y", "x", "x", "y", "z"], "0101110100"], "552": [["y", "x", "y", "x", "x", "z", "z", "z", "x", "z"], "0110111010"], "553": [["z", "x", "y", "y", "z", "x", "y", "y", "z", "x"], "1100011100"], "554": [["z", "z", "x", "y", "y", "z", "z", "y", "z", "z"], "0111110000"], "555": [["z", "y", "x", "z", "y", "x", "z", "z", "y", "y"], "0001010000"], "556": [["z", "x", "x", "z", "x", "z", "x", "y", "y", "x"], "0001100100"], "557": [["z", "z", "z", "x", "z", "x", "z", "x", "y", "x"], "1101010000"], "558": [["x", "y", "z", "x", "y", "x", "z", "z", "y", "y"], "1001000011"], "559": [["z", "y", "x", "x", "z", "y", "x", "z", "z", "x"], "1101010110"], "560": [["y", "z", "x", "z", "y", "z", "y", "z", "z", "y"], "1101100101"], "561": [["z", "y", "x", "x", "x", "y", "x", "y", "x", "z"], "0111001010"], "562": [["y", "z", "y", "x", "y", "z", "y", "y", "z", "x"], "0101101101"], "563": [["z", "x", "z", "y", "y", "y", "y", "x", "z", "x"], "1110000010"], "564": [["z", "y", "y", "y", "y", "x", "z", "z", "y", "x"], "1001010110"], "565": [["z", "z", "y", "x", "y", "y", "x", "y", "z", "z"], "0101100100"], "566": [["y", "y", "z", "y", "x", "z", "z", "x", "z", "x"], "0101110010"], "567": [["y", "y", "z", "z", "z", "z", "z", "z", "y", "x"], "1001110011"], "568": [["y", "z", "y", "y", "x", "y", "x", "z", "z", "z"], "0100100000"], "569": [["z", "z", "y", "y", "z", "z", "z", "z", "z", "z"], "0101111000"], "570": [["y", "z", "y", "y", "y", "x", "z", "x", "y", "x"], "1011000100"], "571": [["y", "x", "y", "y", "x", "y", "y", "x", "x", "z"], "0110100111"], "572": [["y", "y", "z", "x", "z", "z", "x", "z", "z", "x"], "0100111000"], "573": [["x", "z", "x", "x", "y", "y", "x", "z", "x", "x"], "1100100100"], "574": [["x", "x", "y", "y", "x", "y", "y", "z", "x", "x"], "1100011110"], "575": [["z", "z", "x", "x", "z", "y", "y", "x", "x", "x"], "0011111000"], "576": [["y", "x", "y", "z", "x", "x", "x", "x", "z", "y"], "0100000111"], "577": [["y", "y", "z", "x", "z", "x", "y", "z", "x", "y"], "0001011001"], "578": [["y", "x", "x", "y", "x", "y", "z", "z", "x", "x"], "1001101010"], "579": [["z", "y", "x", "y", "y", "x", "z", "x", "y", "y"], "1001100100"], "580": [["y", "z", "z", "y", "z", "z", "z", "y", "x", "x"], "1011111000"], "581": [["x", "x", "y", "z", "x", "x", "x", "x", "y", "z"], "0001100001"], "582": [["z", "x", "z", "x", "y", "y", "z", "z", "z", "z"], "0101011000"], "583": [["y", "x", "x", "z", "z", "y", "y", "z", "z", "z"], "0100110000"], "584": [["z", "x", "y", "z", "x", "z", "x", "x", "z", "z"], "0100100100"], "585": [["z", "y", "z", "x", "y", "y", "y", "x", "y", "y"], "0000010010"], "586": [["z", "x", "z", "y", "z", "z", "z", "y", "x", "x"], "1011111000"], "587": [["x", "z", "x", "x", "y", "y", "z", "z", "y", "x"], "0001101100"], "588": [["x", "z", "x", "x", "x", "y", "z", "x", "z", "x"], "1101001100"], "589": [["x", "z", "y", "y", "y", "y", "y", "z", "z", "z"], "0100010001"], "590": [["z", "y", "y", "z", "x", "y", "y", "x", "y", "x"], "0110010000"], "591": [["y", "z", "x", "y", "z", "y", "y", "x", "z", "z"], "0101010100"], "592": [["z", "x", "x", "x", "y", "z", "x", "z", "y", "z"], "0100111010"], "593": [["z", "y", "z", "z", "y", "z", "y", "z", "x", "z"], "0100110010"], "594": [["x", "x", "x", "z", "z", "y", "y", "y", "x", "x"], "1011110100"], "595": [["z", "x", "y", "x", "z", "y", "y", "y", "y", "x"], "0101110110"], "596": [["z", "z", "y", "z", "z", "z", "x", "z", "z", "x"], "0100110000"], "597": [["x", "x", "y", "y", "x", "y", "x", "x", "x", "x"], "0111101101"], "598": [["x", "x", "x", "x", "x", "z", "x", "z", "x", "z"], "0100101110"], "599": [["z", "z", "x", "y", "y", "x", "z", "y", "x", "x"], "1011100000"], "600": [["z", "x", "y", "y", "z", "y", "z", "y", "x", "y"], "1011011110"], "601": [["y", "z", "z", "x", "x", "z", "y", "z", "x", "x"], "0101110001"], "602": [["x", "z", "y", "z", "x", "y", "z", "x", "x", "x"], "1101010100"], "603": [["z", "y", "y", "z", "x", "z", "y", "z", "y", "x"], "1101110010"], "604": [["y", "x", "x", "z", "x", "x", "y", "y", "x", "y"], "0011100000"], "605": [["x", "z", "z", "z", "x", "y", "y", "y", "y", "x"], "0011100000"], "606": [["x", "x", "x", "z", "y", "x", "y", "x", "z", "z"], "0101101011"], "607": [["y", "y", "x", "z", "y", "x", "y", "x", "y", "x"], "0000000011"], "608": [["y", "y", "x", "y", "y", "z", "x", "y", "y", "x"], "0011111101"], "609": [["x", "y", "x", "z", "y", "z", "x", "x", "x", "y"], "1010110110"], "610": [["x", "y", "z", "x", "y", "x", "z", "z", "z", "z"], "0101010010"], "611": [["x", "y", "y", "x", "y", "y", "y", "z", "z", "y"], "0101010111"], "612": [["y", "y", "y", "z", "x", "z", "y", "x", "z", "z"], "0111110001"], "613": [["z", "z", "y", "x", "z", "x", "y", "y", "z", "z"], "0101011100"], "614": [["y", "z", "x", "z", "z", "y", "y", "z", "x", "x"], "1100010100"], "615": [["x", "z", "z", "z", "x", "z", "y", "y", "y", "x"], "1001100001"], "616": [["y", "z", "z", "x", "z", "x", "y", "y", "x", "y"], "0111110001"], "617": [["y", "x", "x", "y", "z", "z", "z", "z", "y", "z"], "0001111010"], "618": [["x", "y", "x", "z", "z", "y", "z", "z", "x", "y"], "1001010110"], "619": [["z", "y", "z", "z", "x", "x", "y", "y", "z", "x"], "1100110000"], "620": [["y", "y", "z", "z", "x", "y", "z", "x", "x", "y"], "0011110001"], "621": [["y", "z", "y", "x", "x", "x", "x", "z", "y", "z"], "0101010000"], "622": [["z", "z", "x", "z", "x", "y", "z", "x", "y", "y"], "0111100000"], "623": [["y", "z", "x", "x", "x", "z", "y", "z", "x", "y"], "0100110101"], "624": [["x", "x", "z", "y", "z", "x", "y", "x", "z", "y"], "0110010010"], "625": [["x", "y", "y", "z", "y", "x", "y", "z", "z", "z"], "0100100010"], "626": [["z", "x", "z", "z", "z", "y", "x", "z", "z", "z"], "0100010000"], "627": [["x", "x", "z", "y", "x", "y", "z", "z", "z", "x"], "0101001011"], "628": [["y", "y", "z", "y", "z", "y", "x", "z", "z", "z"], "0100110010"], "629": [["x", "z", "y", "y", "z", "z", "z", "y", "z", "y"], "0101111001"], "630": [["z", "y", "y", "y", "y", "z", "x", "y", "y", "x"], "1100111010"], "631": [["y", "y", "y", "z", "x", "z", "y", "y", "y", "z"], "0011110000"], "632": [["y", "z", "x", "z", "x", "y", "y", "x", "z", "x"], "0101000100"], "633": [["x", "z", "z", "y", "z", "y", "y", "x", "y", "z"], "0100110000"], "634": [["y", "y", "z", "y", "x", "z", "x", "z", "x", "x"], "0100100011"], "635": [["y", "y", "z", "z", "y", "y", "y", "x", "x", "z"], "0101110001"], "636": [["y", "y", "z", "x", "z", "y", "z", "x", "x", "z"], "0111011011"], "637": [["x", "x", "z", "x", "y", "z", "x", "y", "z", "y"], "1101111001"], "638": [["z", "x", "y", "y", "y", "z", "z", "z", "z", "z"], "0101100100"], "639": [["z", "y", "z", "x", "x", "x", "y", "z", "x", "y"], "0001001010"], "640": [["y", "x", "x", "z", "z", "z", "y", "x", "y", "x"], "1000110110"], "641": [["y", "z", "y", "x", "x", "z", "x", "y", "z", "x"], "1111101001"], "642": [["y", "y", "x", "x", "y", "y", "z", "x", "x", "y"], "1111111101"], "643": [["y", "x", "z", "z", "z", "x", "z", "z", "z", "y"], "1101010000"], "644": [["y", "x", "y", "y", "x", "x", "z", "y", "x", "z"], "0101000111"], "645": [["x", "x", "z", "x", "x", "z", "x", "y", "x", "y"], "0000110001"], "646": [["x", "z", "z", "x", "y", "x", "x", "x", "x", "y"], "1101000001"], "647": [["y", "z", "x", "z", "y", "z", "x", "z", "y", "x"], "0101110101"], "648": [["y", "z", "y", "x", "x", "x", "x", "x", "x", "x"], "0101111100"], "649": [["y", "z", "z", "y", "z", "x", "z", "z", "z", "z"], "0101111000"], "650": [["z", "y", "z", "y", "z", "x", "x", "z", "y", "y"], "0100011000"], "651": [["z", "z", "y", "y", "z", "x", "z", "y", "z", "x"], "0111110100"], "652": [["x", "z", "z", "y", "z", "z", "z", "x", "x", "y"], "0011110000"], "653": [["z", "y", "x", "y", "x", "y", "z", "z", "y", "z"], "0001000110"], "654": [["x", "z", "z", "y", "x", "y", "z", "y", "z", "z"], "0111010001"], "655": [["y", "y", "z", "z", "x", "z", "y", "x", "z", "z"], "0100110000"], "656": [["x", "y", "y", "y", "y", "z", "x", "x", "z", "y"], "1101111011"], "657": [["y", "z", "x", "x", "z", "x", "y", "y", "x", "y"], "0001111001"], "658": [["y", "z", "y", "y", "z", "x", "x", "x", "x", "x"], "1001111101"], "659": [["z", "x", "z", "x", "x", "x", "z", "z", "y", "y"], "1101100010"], "660": [["x", "z", "x", "z", "z", "z", "z", "x", "y", "x"], "0111110001"], "661": [["z", "y", "z", "y", "x", "z", "x", "y", "x", "y"], "0111101010"], "662": [["y", "x", "x", "x", "z", "z", "z", "x", "z", "z"], "0101110111"], "663": [["z", "z", "z", "x", "x", "z", "z", "y", "z", "x"], "0101101000"], "664": [["z", "z", "y", "z", "y", "y", "x", "y", "y", "z"], "0011000100"], "665": [["y", "z", "y", "y", "y", "y", "z", "z", "y", "z"], "0001011000"], "666": [["z", "z", "y", "x", "x", "y", "x", "x", "x", "y"], "1011110000"], "667": [["z", "y", "x", "x", "x", "y", "z", "x", "y", "y"], "1101000100"], "668": [["z", "z", "x", "y", "y", "y", "z", "x", "y", "z"], "0011101100"], "669": [["y", "z", "y", "y", "y", "z", "y", "x", "z", "x"], "1110111101"], "670": [["y", "y", "y", "x", "z", "z", "y", "z", "y", "x"], "1100110001"], "671": [["y", "y", "y", "x", "z", "z", "z", "z", "x", "x"], "0001110000"], "672": [["y", "x", "y", "z", "z", "y", "x", "z", "y", "x"], "0000010111"], "673": [["z", "x", "z", "x", "y", "y", "x", "z", "y", "x"], "0100001010"], "674": [["x", "y", "x", "z", "x", "x", "z", "y", "x", "y"], "1011100101"], "675": [["y", "y", "y", "z", "x", "z", "z", "z", "y", "y"], "1001110000"], "676": [["x", "y", "x", "z", "z", "z", "x", "z", "z", "x"], "1100110110"], "677": [["y", "x", "z", "z", "z", "x", "z", "y", "z", "y"], "0111110011"], "678": [["z", "y", "z", "z", "z", "y", "x", "x", "x", "z"], "0001110000"], "679": [["x", "x", "y", "x", "z", "x", "y", "y", "z", "x"], "1111011011"], "680": [["x", "y", "x", "y", "x", "x", "y", "y", "z", "y"], "0101010011"], "681": [["y", "z", "x", "z", "x", "z", "x", "y", "z", "z"], "0100110000"], "682": [["y", "x", "y", "x", "y", "z", "z", "y", "y", "x"], "0111101110"], "683": [["x", "y", "x", "z", "x", "z", "x", "z", "y", "z"], "0001110110"], "684": [["y", "z", "z", "y", "z", "z", "x", "y", "x", "y"], "1000111001"], "685": [["z", "z", "x", "y", "x", "y", "y", "x", "z", "x"], "1110111000"], "686": [["z", "z", "x", "z", "y", "y", "x", "y", "y", "x"], "0000010000"], "687": [["z", "x", "y", "z", "z", "x", "x", "x", "z", "z"], "0110110010"], "688": [["z", "z", "z", "z", "y", "x", "z", "z", "x", "y"], "0101010000"], "689": [["y", "x", "x", "y", "x", "x", "x", "y", "z", "z"], "0111111001"], "690": [["x", "y", "z", "x", "x", "x", "z", "y", "y", "y"], "0101000011"], "691": [["x", "z", "z", "z", "y", "x", "y", "x", "x", "x"], "0001010001"], "692": [["x", "y", "x", "z", "y", "z", "x", "y", "y", "z"], "0101100110"], "693": [["z", "y", "y", "z", "x", "y", "y", "x", "y", "y"], "1000000010"], "694": [["y", "z", "x", "z", "x", "y", "y", "z", "z", "z"], "0101110101"], "695": [["z", "z", "y", "x", "y", "z", "y", "z", "z", "x"], "0100110000"], "696": [["z", "z", "y", "x", "z", "z", "x", "x", "z", "z"], "0101110100"], "697": [["x", "x", "x", "y", "z", "y", "z", "z", "x", "x"], "1101110101"], "698": [["y", "z", "x", "z", "z", "y", "y", "z", "x", "y"], "1100010001"], "699": [["y", "x", "x", "z", "y", "z", "x", "x", "y", "z"], "0111110100"], "700": [["y", "z", "z", "x", "z", "x", "x", "z", "y", "z"], "0101111001"], "701": [["x", "y", "y", "x", "x", "y", "z", "z", "x", "x"], "0101011001"], "702": [["y", "y", "z", "x", "z", "x", "z", "y", "y", "y"], "1101110000"], "703": [["x", "y", "y", "y", "z", "y", "x", "y", "x", "z"], "0010110100"], "704": [["x", "y", "y", "y", "x", "z", "y", "x", "z", "x"], "0110100110"], "705": [["x", "z", "x", "x", "x", "z", "x", "y", "z", "z"], "0100110000"], "706": [["x", "x", "x", "z", "y", "z", "z", "x", "y", "y"], "1101100011"], "707": [["y", "y", "z", "y", "y", "y", "x", "z", "x", "x"], "1101100011"], "708": [["z", "y", "x", "z", "x", "z", "x", "z", "x", "y"], "0000100010"], "709": [["y", "z", "z", "z", "x", "z", "z", "y", "x", "y"], "0111110001"], "710": [["y", "y", "z", "x", "z", "z", "y", "y", "x", "x"], "0100110001"], "711": [["z", "x", "z", "y", "y", "x", "y", "z", "y", "z"], "0101100000"], "712": [["y", "x", "y", "y", "x", "y", "x", "x", "z", "x"], "1101011101"], "713": [["z", "y", "z", "x", "z", "x", "x", "z", "z", "x"], "1100010010"], "714": [["y", "z", "x", "y", "z", "x", "z", "x", "z", "y"], "0111111101"], "715": [["z", "y", "x", "x", "z", "z", "z", "z", "y", "x"], "0001110100"], "716": [["y", "z", "z", "x", "z", "x", "x", "z", "y", "y"], "1001010000"], "717": [["y", "x", "z", "z", "y", "x", "y", "z", "y", "y"], "0000010011"], "718": [["y", "x", "y", "y", "y", "y", "z", "x", "z", "y"], "1101011010"], "719": [["z", "y", "x", "y", "y", "x", "z", "x", "x", "y"], "0111001010"], "720": [["z", "x", "y", "z", "x", "y", "z", "z", "y", "x"], "1101010110"], "721": [["x", "z", "x", "x", "z", "z", "y", "z", "x", "x"], "0001111100"], "722": [["z", "z", "z", "z", "y", "x", "y", "z", "y", "y"], "0000110000"], "723": [["y", "z", "z", "y", "x", "z", "z", "z", "z", "y"], "1101101000"], "724": [["z", "z", "y", "x", "x", "y", "z", "x", "y", "z"], "0111100000"], "725": [["y", "y", "y", "x", "y", "y", "y", "x", "z", "z"], "0110110110"], "726": [["z", "x", "z", "x", "y", "x", "z", "y", "y", "x"], "0001110010"], "727": [["y", "x", "y", "x", "x", "y", "x", "y", "z", "y"], "1100000010"], "728": [["x", "y", "x", "z", "x", "z", "y", "z", "y", "z"], "0001100000"], "729": [["y", "y", "y", "z", "x", "z", "x", "x", "x", "y"], "1111100100"], "730": [["x", "x", "z", "x", "x", "x", "y", "z", "y", "y"], "0100111000"], "731": [["x", "y", "y", "x", "y", "z", "x", "z", "z", "x"], "1100111101"], "732": [["x", "z", "x", "z", "x", "z", "z", "x", "y", "x"], "0011100100"], "733": [["z", "z", "x", "y", "x", "y", "x", "x", "x", "y"], "0010001100"], "734": [["y", "z", "z", "z", "z", "z", "z", "x", "x", "z"], "0111110000"], "735": [["y", "y", "x", "x", "x", "y", "z", "y", "x", "x"], "1111000010"], "736": [["x", "x", "x", "x", "x", "x", "z", "y", "z", "z"], "0101101101"], "737": [["y", "y", "x", "z", "x", "x", "z", "x", "y", "z"], "0111010101"], "738": [["z", "z", "x", "x", "z", "y", "y", "y", "z", "x"], "0110011000"], "739": [["z", "x", "z", "z", "x", "z", "y", "y", "z", "x"], "1111110010"], "740": [["z", "x", "z", "y", "y", "z", "x", "z", "x", "y"], "0001110000"], "741": [["x", "z", "x", "z", "x", "y", "x", "z", "z", "y"], "0101110100"], "742": [["z", "z", "z", "z", "y", "z", "z", "y", "x", "y"], "0001110000"], "743": [["y", "y", "x", "y", "x", "z", "y", "y", "x", "y"], "0010110011"], "744": [["x", "z", "z", "y", "y", "z", "x", "z", "x", "y"], "0000100001"], "745": [["x", "x", "x", "x", "x", "y", "z", "z", "z", "y"], "1101111101"], "746": [["x", "y", "z", "z", "z", "z", "y", "x", "y", "y"], "0011110000"], "747": [["z", "x", "x", "z", "y", "x", "x", "y", "y", "x"], "0101100010"], "748": [["x", "x", "y", "z", "y", "y", "y", "x", "z", "z"], "0110010010"], "749": [["z", "x", "y", "y", "z", "x", "x", "y", "y", "x"], "0111010100"], "750": [["x", "z", "x", "x", "z", "z", "z", "z", "y", "y"], "0001110001"], "751": [["y", "z", "y", "y", "x", "z", "x", "x", "z", "y"], "1100110101"], "752": [["z", "x", "y", "z", "y", "y", "z", "y", "x", "y"], "0111010000"], "753": [["x", "y", "y", "z", "x", "x", "x", "y", "x", "z"], "0111110010"], "754": [["y", "y", "y", "x", "x", "y", "x", "z", "x", "y"], "0101111100"], "755": [["z", "z", "x", "x", "z", "z", "y", "z", "x", "y"], "0101110000"], "756": [["z", "z", "y", "x", "z", "z", "z", "y", "y", "y"], "1011111000"], "757": [["y", "z", "x", "y", "z", "z", "y", "y", "x", "x"], "1010110001"], "758": [["z", "z", "y", "y", "z", "x", "y", "z", "x", "z"], "0100011000"], "759": [["z", "z", "y", "x", "z", "z", "x", "y", "x", "z"], "0111110100"], "760": [["x", "x", "z", "y", "z", "y", "x", "z", "y", "y"], "1101111001"], "761": [["x", "x", "y", "y", "x", "x", "y", "z", "z", "y"], "0100101011"], "762": [["y", "x", "x", "z", "z", "y", "y", "z", "z", "y"], "1100010111"], "763": [["y", "z", "z", "y", "x", "x", "z", "x", "x", "y"], "1101101000"], "764": [["z", "x", "z", "z", "y", "z", "z", "z", "z", "z"], "0101110010"], "765": [["x", "x", "z", "x", "y", "y", "y", "y", "y", "x"], "1000100010"], "766": [["y", "x", "y", "x", "x", "x", "z", "z", "z", "y"], "0101010010"], "767": [["z", "x", "y", "z", "y", "y", "x", "z", "x", "y"], "0101100100"], "768": [["x", "x", "x", "z", "x", "x", "z", "x", "z", "x"], "1111000100"], "769": [["x", "x", "y", "y", "z", "x", "y", "x", "y", "x"], "0010011110"], "770": [["y", "y", "z", "x", "z", "y", "y", "x", "y", "x"], "1000110000"], "771": [["x", "x", "x", "z", "x", "z", "y", "y", "y", "x"], "0000110111"], "772": [["x", "x", "x", "z", "z", "z", "y", "x", "z", "z"], "0111110111"], "773": [["y", "y", "z", "x", "z", "z", "y", "y", "x", "z"], "0011111000"], "774": [["x", "z", "x", "y", "y", "z", "x", "z", "z", "y"], "1101111001"], "775": [["x", "x", "x", "y", "y", "z", "x", "x", "x", "x"], "0101101100"], "776": [["x", "x", "z", "y", "y", "y", "z", "y", "x", "x"], "1111001000"], "777": [["x", "z", "y", "x", "y", "x", "y", "x", "z", "x"], "1101101100"], "778": [["y", "x", "x", "z", "x", "x", "y", "y", "y", "z"], "0000101110"], "779": [["z", "x", "y", "z", "y", "z", "y", "y", "y", "z"], "0010110110"], "780": [["y", "y", "x", "z", "y", "x", "x", "z", "y", "z"], "0001110101"], "781": [["z", "x", "y", "z", "y", "z", "y", "x", "z", "x"], "0101110000"], "782": [["z", "y", "x", "y", "x", "x", "z", "z", "z", "z"], "0101000100"], "783": [["y", "z", "x", "y", "y", "z", "x", "y", "y", "y"], "1000110101"], "784": [["z", "z", "z", "z", "y", "z", "x", "y", "x", "z"], "0010110000"], "785": [["y", "z", "x", "y", "y", "y", "y", "y", "z", "y"], "1100101101"], "786": [["x", "y", "y", "x", "y", "y", "y", "x", "x", "z"], "0011010101"], "787": [["z", "y", "z", "x", "y", "z", "y", "x", "y", "x"], "0110111010"], "788": [["y", "x", "y", "y", "z", "x", "y", "x", "y", "z"], "0111011001"], "789": [["x", "y", "y", "y", "x", "y", "x", "z", "x", "y"], "1001110100"], "790": [["y", "y", "y", "z", "z", "z", "x", "y", "z", "y"], "0101110101"], "791": [["z", "x", "y", "z", "z", "y", "y", "z", "x", "z"], "0001110100"], "792": [["x", "y", "y", "z", "y", "z", "z", "x", "y", "x"], "1101110001"], "793": [["x", "z", "z", "z", "z", "z", "z", "x", "x", "y"], "0111110001"], "794": [["z", "x", "z", "x", "z", "z", "z", "x", "z", "y"], "1111110010"], "795": [["y", "y", "z", "z", "y", "z", "y", "y", "x", "x"], "0100110010"], "796": [["z", "x", "x", "y", "y", "x", "y", "y", "y", "z"], "0010001100"], "797": [["y", "z", "y", "z", "x", "z", "y", "y", "y", "z"], "0101110000"], "798": [["x", "x", "x", "z", "x", "z", "z", "z", "y", "z"], "0001110011"], "799": [["y", "z", "z", "z", "y", "z", "y", "y", "z", "x"], "1110110000"], "800": [["x", "z", "z", "x", "y", "z", "x", "y", "z", "x"], "1101110000"], "801": [["x", "z", "x", "z", "z", "x", "z", "x", "z", "y"], "0101010101"], "802": [["y", "y", "y", "y", "y", "y", "z", "y", "y", "z"], "0100010000"], "803": [["z", "y", "x", "z", "y", "x", "x", "x", "y", "z"], "0110100010"], "804": [["z", "z", "z", "y", "z", "z", "z", "x", "z", "y"], "0101111000"], "805": [["x", "y", "x", "z", "y", "x", "z", "x", "z", "y"], "1101010110"], "806": [["x", "z", "z", "y", "x", "z", "x", "y", "x", "z"], "0100101001"], "807": [["z", "x", "x", "x", "y", "z", "y", "x", "z", "y"], "0100101010"], "808": [["z", "x", "z", "z", "x", "z", "x", "z", "z", "x"], "0101110000"], "809": [["z", "x", "z", "y", "y", "x", "x", "y", "z", "x"], "0101000010"], "810": [["y", "z", "x", "x", "x", "x", "x", "y", "x", "y"], "0000100100"], "811": [["x", "z", "y", "y", "z", "z", "y", "x", "y", "y"], "0111110100"], "812": [["y", "x", "y", "x", "z", "x", "y", "z", "z", "y"], "0101011000"], "813": [["x", "y", "z", "z", "x", "z", "x", "y", "x", "y"], "0110100010"], "814": [["y", "y", "y", "z", "x", "y", "x", "y", "y", "y"], "1010000111"], "815": [["y", "x", "y", "x", "z", "z", "x", "x", "z", "x"], "0101111101"], "816": [["z", "z", "x", "y", "x", "x", "y", "y", "y", "y"], "1011010000"], "817": [["x", "x", "z", "x", "z", "y", "x", "z", "z", "y"], "1100011000"], "818": [["x", "y", "x", "z", "y", "z", "z", "y", "z", "z"], "0101100011"], "819": [["z", "x", "z", "x", "y", "z", "y", "y", "y", "y"], "0100100010"], "820": [["x", "z", "y", "x", "x", "y", "x", "z", "x", "x"], "1101011001"], "821": [["z", "y", "y", "z", "x", "z", "z", "z", "x", "x"], "1001110110"], "822": [["x", "x", "x", "x", "z", "x", "x", "y", "x", "x"], "1100011011"], "823": [["z", "x", "z", "z", "y", "z", "y", "z", "z", "z"], "0101100010"], "824": [["y", "x", "x", "x", "y", "z", "z", "y", "z", "y"], "0111100000"], "825": [["z", "x", "x", "y", "x", "x", "z", "x", "y", "y"], "0001001000"], "826": [["z", "y", "z", "z", "x", "x", "z", "x", "z", "y"], "0111110000"], "827": [["x", "x", "z", "z", "y", "x", "x", "x", "y", "y"], "0110110000"], "828": [["y", "z", "z", "x", "x", "y", "z", "z", "y", "z"], "0001110001"], "829": [["y", "z", "y", "x", "y", "y", "x", "y", "z", "x"], "0110101101"], "830": [["y", "y", "x", "y", "y", "x", "z", "y", "x", "x"], "1101110010"], "831": [["z", "y", "y", "x", "z", "x", "x", "z", "z", "x"], "0100010110"], "832": [["z", "y", "y", "x", "z", "x", "y", "x", "z", "x"], "0111010000"], "833": [["y", "z", "z", "z", "z", "x", "y", "y", "x", "x"], "0101110000"], "834": [["z", "z", "z", "x", "x", "y", "z", "y", "x", "x"], "0101000000"], "835": [["z", "y", "y", "x", "y", "y", "x", "y", "y", "y"], "0011100100"], "836": [["x", "x", "z", "y", "y", "x", "z", "y", "x", "x"], "1111111010"], "837": [["z", "y", "z", "x", "y", "z", "z", "y", "y", "y"], "0101101000"], "838": [["y", "z", "y", "x", "z", "x", "y", "y", "y", "y"], "0010111100"], "839": [["y", "y", "x", "y", "y", "y", "y", "z", "x", "x"], "0000011100"], "840": [["x", "x", "y", "y", "x", "x", "x", "z", "x", "z"], "0100000111"], "841": [["y", "y", "z", "z", "z", "z", "x", "y", "y", "z"], "0100110010"], "842": [["y", "x", "y", "z", "z", "y", "y", "x", "z", "x"], "1111110111"], "843": [["y", "y", "z", "y", "x", "z", "z", "y", "x", "x"], "0111111011"], "844": [["z", "z", "x", "x", "z", "y", "z", "x", "y", "x"], "0101111000"], "845": [["z", "y", "x", "y", "x", "z", "x", "z", "x", "x"], "1001101010"], "846": [["y", "x", "z", "z", "y", "y", "y", "z", "z", "z"], "0101110010"], "847": [["z", "x", "z", "y", "x", "x", "z", "x", "x", "x"], "1011101000"], "848": [["x", "x", "x", "z", "x", "z", "y", "z", "y", "z"], "0101100011"], "849": [["y", "y", "x", "z", "z", "x", "y", "y", "y", "z"], "0011010110"], "850": [["z", "z", "x", "x", "z", "x", "z", "z", "y", "x"], "0101110000"], "851": [["z", "x", "x", "z", "y", "y", "z", "z", "x", "z"], "0101000000"], "852": [["y", "y", "y", "x", "x", "z", "y", "y", "y", "y"], "1100101011"], "853": [["z", "x", "z", "x", "z", "x", "y", "z", "z", "y"], "1101011010"], "854": [["y", "y", "y", "z", "x", "x", "y", "x", "x", "z"], "0000010010"], "855": [["z", "x", "z", "z", "x", "z", "z", "y", "z", "z"], "0101100000"], "856": [["y", "y", "x", "y", "x", "y", "y", "y", "x", "z"], "0111110110"], "857": [["y", "y", "x", "y", "z", "z", "z", "x", "x", "y"], "1011111101"], "858": [["y", "z", "x", "y", "z", "y", "y", "y", "z", "x"], "0100010001"], "859": [["y", "x", "y", "y", "y", "y", "x", "y", "y", "x"], "1101011000"], "860": [["y", "z", "x", "z", "y", "x", "z", "z", "x", "y"], "1001000101"], "861": [["x", "x", "x", "z", "x", "y", "y", "z", "z", "y"], "0100010001"], "862": [["y", "y", "z", "z", "z", "z", "x", "y", "y", "x"], "1010110001"], "863": [["x", "y", "y", "x", "y", "y", "y", "z", "z", "x"], "0100100001"], "864": [["x", "x", "y", "y", "x", "z", "y", "z", "z", "x"], "1100101111"], "865": [["x", "y", "x", "z", "z", "y", "y", "y", "z", "z"], "0110010001"], "866": [["z", "y", "z", "x", "z", "y", "y", "z", "y", "z"], "0100011000"], "867": [["y", "z", "y", "x", "z", "x", "y", "x", "y", "y"], "0000010000"], "868": [["x", "z", "z", "z", "z", "y", "y", "x", "x", "x"], "0100110001"], "869": [["x", "y", "x", "z", "x", "z", "x", "y", "x", "y"], "1011100010"], "870": [["x", "x", "y", "y", "x", "x", "z", "z", "z", "y"], "0101000110"], "871": [["x", "y", "y", "y", "z", "y", "y", "x", "y", "z"], "0101110101"], "872": [["x", "z", "z", "y", "x", "x", "z", "z", "z", "y"], "1101100000"], "873": [["x", "x", "y", "z", "z", "y", "z", "x", "y", "z"], "0001010010"], "874": [["y", "y", "z", "x", "z", "y", "z", "z", "y", "x"], "1001011011"], "875": [["y", "y", "y", "x", "y", "y", "x", "y", "x", "y"], "0111000001"], "876": [["z", "y", "x", "y", "x", "y", "y", "x", "x", "x"], "0010000000"], "877": [["x", "z", "z", "y", "x", "x", "y", "x", "y", "x"], "1100111001"], "878": [["y", "y", "x", "z", "x", "z", "z", "z", "z", "z"], "0101110001"], "879": [["y", "y", "z", "z", "z", "x", "x", "x", "x", "x"], "1011110010"], "880": [["y", "x", "y", "z", "x", "y", "y", "x", "z", "x"], "1101010001"], "881": [["z", "z", "z", "y", "x", "z", "x", "x", "z", "x"], "0100110000"], "882": [["z", "x", "x", "x", "y", "y", "z", "z", "y", "x"], "0100010100"], "883": [["y", "z", "x", "x", "z", "z", "z", "x", "y", "y"], "1001111100"], "884": [["z", "y", "z", "x", "x", "x", "y", "y", "x", "z"], "0101000010"], "885": [["x", "y", "x", "y", "y", "x", "x", "x", "x", "x"], "1010001110"], "886": [["y", "x", "z", "z", "x", "x", "y", "z", "y", "x"], "0100010011"], "887": [["z", "z", "y", "z", "z", "y", "x", "z", "x", "x"], "0111011001"], "888": [["y", "y", "z", "z", "z", "y", "y", "y", "y", "z"], "0100110001"], "889": [["z", "z", "y", "z", "x", "y", "z", "z", "y", "z"], "0001110000"], "890": [["x", "y", "y", "y", "y", "y", "y", "x", "z", "y"], "0111001001"], "891": [["y", "x", "y", "z", "x", "x", "y", "z", "z", "z"], "0101100000"], "892": [["x", "z", "x", "y", "x", "y", "y", "x", "z", "y"], "1110101000"], "893": [["y", "x", "z", "x", "y", "x", "y", "z", "y", "x"], "1100101001"], "894": [["z", "y", "z", "x", "x", "z", "y", "z", "x", "y"], "1100100010"], "895": [["y", "x", "y", "x", "y", "y", "x", "y", "z", "x"], "1101001001"], "896": [["x", "z", "z", "y", "x", "z", "z", "y", "z", "z"], "0111110000"], "897": [["y", "x", "z", "x", "x", "x", "x", "x", "x", "y"], "0001110011"], "898": [["y", "z", "z", "z", "x", "y", "z", "y", "y", "z"], "0101000000"], "899": [["z", "z", "z", "y", "z", "x", "z", "z", "y", "y"], "0001111000"], "900": [["y", "x", "x", "z", "y", "y", "z", "z", "y", "y"], "0101010100"], "901": [["y", "z", "x", "y", "z", "x", "y", "y", "x", "y"], "0010011000"], "902": [["z", "z", "y", "x", "z", "z", "z", "z", "z", "y"], "1101110100"], "903": [["x", "x", "x", "y", "x", "x", "y", "x", "x", "z"], "0000111111"], "904": [["y", "x", "y", "z", "y", "y", "x", "z", "x", "y"], "0100110100"], "905": [["y", "x", "y", "y", "y", "z", "z", "y", "x", "y"], "1011110100"], "906": [["x", "y", "y", "x", "z", "x", "y", "y", "y", "y"], "1011110110"], "907": [["x", "x", "z", "y", "x", "x", "y", "y", "z", "z"], "0110101010"], "908": [["y", "y", "x", "x", "y", "y", "z", "z", "z", "z"], "0101110111"], "909": [["z", "x", "z", "x", "x", "z", "z", "z", "x", "z"], "0101100000"], "910": [["x", "z", "z", "y", "z", "z", "x", "x", "z", "x"], "0110111001"], "911": [["x", "x", "z", "x", "y", "x", "y", "z", "y", "z"], "0001111000"], "912": [["z", "y", "z", "y", "x", "x", "z", "z", "y", "z"], "0101110010"], "913": [["y", "y", "z", "z", "x", "z", "y", "z", "y", "z"], "0000110000"], "914": [["x", "x", "z", "z", "x", "z", "x", "y", "x", "z"], "0011100010"], "915": [["x", "x", "x", "x", "x", "y", "y", "x", "x", "y"], "0001010011"], "916": [["x", "y", "x", "z", "z", "z", "z", "y", "z", "y"], "1111110110"], "917": [["y", "x", "y", "z", "y", "y", "y", "y", "x", "x"], "0100100011"], "918": [["z", "z", "y", "x", "y", "z", "z", "x", "z", "y"], "0101100000"], "919": [["z", "y", "z", "z", "x", "x", "y", "y", "x", "y"], "0110110010"], "920": [["y", "x", "y", "z", "z", "y", "y", "x", "y", "z"], "0001010000"], "921": [["y", "z", "z", "y", "z", "y", "x", "x", "z", "x"], "0100011001"], "922": [["y", "x", "y", "z", "y", "y", "z", "x", "z", "y"], "0111110010"], "923": [["y", "z", "z", "x", "z", "x", "x", "x", "z", "x"], "0100010001"], "924": [["z", "z", "y", "z", "x", "z", "y", "x", "z", "z"], "0101110100"], "925": [["y", "y", "y", "y", "z", "x", "y", "y", "x", "x"], "1101110100"], "926": [["x", "z", "z", "x", "x", "y", "x", "y", "x", "y"], "0110001000"], "927": [["y", "z", "y", "y", "z", "z", "z", "y", "z", "y"], "1101110100"], "928": [["y", "y", "z", "x", "y", "x", "x", "x", "z", "x"], "0101010001"], "929": [["x", "x", "z", "x", "y", "y", "z", "x", "z", "x"], "1111110011"], "930": [["y", "x", "y", "z", "x", "x", "x", "x", "z", "y"], "1101100010"], "931": [["x", "y", "y", "z", "y", "z", "y", "z", "z", "y"], "1100100101"], "932": [["y", "x", "z", "x", "y", "z", "y", "x", "x", "x"], "0011100010"], "933": [["y", "x", "x", "y", "z", "y", "z", "x", "z", "x"], "0111111000"], "934": [["z", "y", "z", "x", "z", "z", "y", "z", "x", "z"], "0101110000"], "935": [["x", "y", "y", "x", "z", "z", "y", "x", "z", "x"], "1111111001"], "936": [["x", "z", "y", "z", "z", "z", "x", "x", "x", "z"], "0011110101"], "937": [["x", "z", "x", "y", "z", "x", "x", "x", "z", "x"], "1110110000"], "938": [["x", "x", "x", "z", "y", "y", "y", "y", "x", "z"], "0100100111"], "939": [["z", "x", "z", "x", "x", "z", "z", "y", "x", "y"], "0001101010"], "940": [["x", "x", "z", "y", "z", "x", "z", "y", "y", "y"], "1111010011"], "941": [["y", "x", "y", "x", "x", "z", "x", "y", "y", "y"], "0111110100"], "942": [["z", "z", "x", "x", "x", "y", "x", "y", "x", "z"], "0110101000"], "943": [["x", "x", "z", "y", "x", "x", "y", "z", "z", "z"], "0101100010"], "944": [["y", "z", "x", "z", "z", "z", "x", "z", "y", "y"], "1000110101"], "945": [["z", "x", "z", "y", "z", "x", "y", "z", "x", "x"], "1100111010"], "946": [["z", "z", "z", "x", "z", "y", "y", "y", "x", "x"], "1010011000"], "947": [["z", "x", "x", "x", "x", "x", "y", "y", "y", "x"], "1110101010"], "948": [["x", "x", "z", "y", "y", "y", "z", "y", "x", "y"], "0001010001"], "949": [["z", "x", "y", "z", "y", "z", "x", "x", "z", "z"], "0100100000"], "950": [["z", "z", "x", "x", "z", "z", "z", "z", "x", "x"], "0101110000"], "951": [["y", "y", "y", "y", "y", "z", "y", "y", "y", "x"], "0000111100"], "952": [["x", "y", "y", "x", "x", "z", "x", "x", "z", "y"], "0111111000"], "953": [["y", "z", "x", "x", "y", "z", "z", "y", "y", "y"], "1101110100"], "954": [["x", "x", "x", "x", "y", "y", "y", "z", "z", "y"], "0101110111"], "955": [["z", "y", "x", "x", "x", "x", "x", "z", "y", "y"], "0000100100"], "956": [["x", "y", "x", "x", "z", "x", "x", "x", "x", "z"], "0101010111"], "957": [["y", "x", "z", "x", "z", "x", "z", "z", "y", "x"], "0101011011"], "958": [["y", "x", "y", "x", "z", "y", "y", "z", "y", "y"], "0100111000"], "959": [["z", "x", "y", "y", "y", "z", "y", "z", "z", "x"], "0100111110"], "960": [["z", "y", "y", "y", "x", "x", "x", "x", "y", "z"], "0010101010"], "961": [["x", "z", "z", "y", "x", "z", "y", "x", "y", "x"], "1010110001"], "962": [["z", "y", "z", "z", "x", "z", "y", "z", "z", "y"], "0101100000"], "963": [["z", "z", "y", "x", "z", "z", "x", "x", "z", "y"], "1101111000"], "964": [["x", "y", "x", "x", "x", "x", "z", "y", "x", "y"], "0101011010"], "965": [["x", "x", "x", "z", "x", "y", "x", "z", "x", "x"], "0001010000"], "966": [["x", "y", "z", "y", "y", "z", "z", "z", "x", "x"], "0001100000"], "967": [["y", "y", "y", "y", "x", "y", "x", "x", "x", "y"], "0101011111"], "968": [["x", "z", "z", "y", "z", "y", "z", "z", "y", "z"], "0001010001"], "969": [["x", "x", "x", "y", "z", "x", "x", "z", "x", "z"], "0101111100"], "970": [["y", "y", "z", "z", "z", "x", "x", "y", "z", "z"], "0100010010"], "971": [["x", "y", "y", "z", "x", "x", "z", "z", "x", "y"], "1001110001"], "972": [["z", "x", "y", "z", "z", "y", "x", "z", "x", "y"], "1000010010"], "973": [["y", "z", "y", "z", "y", "y", "x", "y", "x", "x"], "0000100100"], "974": [["z", "y", "y", "x", "x", "x", "z", "x", "x", "y"], "0101100110"], "975": [["y", "y", "z", "y", "y", "y", "z", "z", "z", "z"], "0101001000"], "976": [["y", "z", "z", "z", "x", "y", "z", "x", "y", "y"], "1001010000"], "977": [["z", "x", "x", "z", "x", "y", "y", "y", "x", "z"], "0101100000"], "978": [["x", "z", "x", "z", "z", "x", "x", "z", "z", "x"], "1100010101"], "979": [["y", "y", "z", "z", "y", "z", "z", "x", "x", "z"], "0101100010"], "980": [["x", "x", "y", "y", "y", "z", "y", "z", "z", "y"], "0101110001"], "981": [["z", "y", "x", "x", "z", "y", "y", "x", "z", "y"], "0111010000"], "982": [["z", "x", "x", "y", "x", "x", "z", "y", "y", "y"], "1001110000"], "983": [["z", "x", "y", "x", "x", "y", "z", "z", "y", "x"], "0001101100"], "984": [["z", "z", "x", "y", "z", "x", "x", "y", "x", "x"], "1100010100"], "985": [["y", "y", "x", "y", "x", "y", "y", "x", "y", "y"], "0100111000"], "986": [["y", "z", "y", "z", "x", "z", "y", "y", "y", "x"], "1101100101"], "987": [["x", "y", "z", "y", "x", "y", "x", "y", "z", "y"], "0101110011"], "988": [["y", "x", "y", "x", "x", "z", "z", "y", "z", "y"], "0101101011"], "989": [["z", "x", "y", "z", "y", "x", "x", "x", "x", "z"], "0010100010"], "990": [["y", "z", "y", "x", "z", "x", "x", "x", "y", "x"], "0101110001"], "991": [["z", "y", "y", "x", "y", "y", "y", "y", "y", "z"], "0000111010"], "992": [["z", "z", "x", "x", "y", "z", "y", "y", "z", "z"], "0100110000"], "993": [["x", "y", "x", "x", "x", "z", "z", "y", "y", "x"], "1101100101"], "994": [["z", "y", "y", "z", "z", "z", "z", "x", "y", "z"], "0011110100"], "995": [["z", "x", "z", "y", "z", "x", "y", "z", "z", "y"], "0101110010"], "996": [["z", "x", "y", "y", "y", "z", "x", "y", "z", "y"], "0111101010"], "997": [["z", "x", "z", "x", "z", "y", "z", "x", "y", "z"], "0011011000"], "998": [["y", "z", "z", "y", "x", "z", "z", "y", "x", "z"], "0101101000"], "999": [["z", "y", "x", "x", "x", "z", "y", "y", "x", "y"], "1100100110"]}}